taskiq_pg/__init__.py
taskiq_pg/_internal/__init__.py
taskiq_pg/_internal/broker.py
taskiq_pg/_internal/result_backend.py
taskiq_pg/_internal/schedule_source.py
taskiq_pg/aiopg/__init__.py
taskiq_pg/aiopg/broker.py
taskiq_pg/aiopg/queries.py
taskiq_pg/aiopg/result_backend.py
taskiq_pg/aiopg/schedule_source.py
taskiq_pg/asyncpg/__init__.py
taskiq_pg/asyncpg/broker.py
taskiq_pg/asyncpg/queries.py
taskiq_pg/asyncpg/result_backend.py
taskiq_pg/asyncpg/schedule_source.py
taskiq_pg/exceptions.py
taskiq_pg/psqlpy/__init__.py
taskiq_pg/psqlpy/broker.py
taskiq_pg/psqlpy/queries.py
taskiq_pg/psqlpy/result_backend.py
taskiq_pg/psqlpy/schedule_source.py
taskiq_pg/psycopg/__init__.py
taskiq_pg/psycopg/broker.py
taskiq_pg/psycopg/queries.py
taskiq_pg/psycopg/result_backend.py
taskiq_pg/psycopg/schedule_source.py
taskiq_pg/py.typed
taskiq_postgres-0.7.0.dist-info/licenses/LICENSE
taskiq_postgres-0.7.0.dist-info/WHEEL
taskiq_postgres-0.7.0.dist-info/METADATA
taskiq_postgres-0.7.0.dist-info/RECORD
