Metadata-Version: 2.4
Name: taskiq-postgres
Version: 0.7.0
Summary: PostgreSQL integration for taskiq
Keywords: taskiq,tasks,distributed,async,postgresql
Author: Anfimov Dima
Author-email: Anfimov Dima <lovesolaristics@gmail.com>
License-Expression: MIT
License-File: LICENSE
Classifier: Development Status :: 5 - Production/Stable
Classifier: Intended Audience :: Developers
Classifier: Intended Audience :: Information Technology
Classifier: Framework :: AsyncIO
Classifier: License :: OSI Approved :: MIT License
Classifier: Programming Language :: Python
Classifier: Programming Language :: Python :: 3
Classifier: Programming Language :: Python :: 3 :: Only
Classifier: Programming Language :: Python :: 3.10
Classifier: Programming Language :: Python :: 3.11
Classifier: Programming Language :: Python :: 3.12
Classifier: Programming Language :: Python :: 3.13
Classifier: Programming Language :: Python :: 3.14
Classifier: Programming Language :: Python :: Implementation :: CPython
Classifier: Topic :: Software Development :: Libraries :: Python Modules
Classifier: Topic :: Software Development :: Libraries
Classifier: Topic :: Software Development
Classifier: Topic :: System :: Networking
Classifier: Typing :: Typed
Classifier: Operating System :: OS Independent
Requires-Dist: taskiq>=0.12.0
Requires-Dist: aiopg>=1.4.0 ; extra == 'aiopg'
Requires-Dist: asyncpg>=0.31.0 ; extra == 'asyncpg'
Requires-Dist: psqlpy>=0.11.11 ; extra == 'psqlpy'
Requires-Dist: psycopg[binary,pool]>=3.3.2 ; extra == 'psycopg'
Requires-Python: >=3.10, <3.15
Project-URL: Bug Tracker, https://github.com/danfimov/taskiq-postgres/issues
Project-URL: Repository, https://github.com/danfimov/taskiq-postgres/
Provides-Extra: aiopg
Provides-Extra: asyncpg
Provides-Extra: psqlpy
Provides-Extra: psycopg
